[
  {
    "name": "SNID",
    "value": "AKwSQFmZEOH4MbO9LGurDidAhBgEAC9JLV5RwdKaLQOQqk55Y5jIMh1Ku4xWUphLCnW7RDrZUhcCt4eG-q0TcoWl-UpQ17dx9g",
    "domain": ".google.com",
    "hostOnly": false,
    "path": "/verify",
    "secure": true,
    "httpOnly": true,
    "session": false,
    "expirationDate": 1743002118.116515,
    "sameSite": "lax"
  },
  {
    "name": "_octo",
    "value": "GH1.1.514941751.1727166470",
    "domain": ".github.com",
    "hostOnly": false,
    "path": "/",
    "secure": true,
    "httpOnly": false,
    "session": false,
    "expirationDate": 1758702480.344762,
    "sameSite": "lax"
  },
  {
    "name": "_device_id",
    "value": "e143e91b887e2be80e941ed5e6479f72",
    "domain": "github.com",
    "hostOnly": true,
    "path": "/",
    "secure": true,
    "httpOnly": true,
    "session": false,
    "expirationDate": 1758702477.493795,
    "sameSite": "lax"
  },
  {
    "name": "saved_user_sessions",
    "value": "182425578%3A9AlGX9rEqRWbTsOO9JSRP8hgKmyONDfEjsZUWwNffEvfQiIm",
    "domain": "github.com",
    "hostOnly": true,
    "path": "/",
    "secure": true,
    "httpOnly": true,
    "session": false,
    "expirationDate": 1734946374.386816,
    "sameSite": "lax"
  },
  {
    "name": "user_session",
    "value": "9AlGX9rEqRWbTsOO9JSRP8hgKmyONDfEjsZUWwNffEvfQiIm",
    "domain": "github.com",
    "hostOnly": true,
    "path": "/",
    "secure": true,
    "httpOnly": true,
    "session": false,
    "expirationDate": 1728376374.387052,
    "sameSite": "lax"
  },
  {
    "name": "__Host-user_session_same_site",
    "value": "9AlGX9rEqRWbTsOO9JSRP8hgKmyONDfEjsZUWwNffEvfQiIm",
    "domain": "github.com",
    "hostOnly": true,
    "path": "/",
    "secure": true,
    "httpOnly": true,
    "session": false,
    "expirationDate": 1728376374.387162,
    "sameSite": "strict"
  },
  {
    "name": "logged_in",
    "value": "yes",
    "domain": ".github.com",
    "hostOnly": false,
    "path": "/",
    "secure": true,
    "httpOnly": true,
    "session": false,
    "expirationDate": 1758702774.38737,
    "sameSite": "lax"
  },
  {
    "name": "dotcom_user",
    "value": "mohammedsaleh111",
    "domain": ".github.com",
    "hostOnly": false,
    "path": "/",
    "secure": true,
    "httpOnly": true,
    "session": false,
    "expirationDate": 1758702774.387532,
    "sameSite": "lax"
  },
  {
    "name": "AEC",
    "value": "AVYB7cpkkfbfAh1d97Z5X4dwdhUziUhhefjyr12Y1qg4UPJrGnUi0xkAmV4",
    "domain": ".google.com",
    "hostOnly": false,
    "path": "/",
    "secure": true,
    "httpOnly": true,
    "session": false,
    "expirationDate": 1742734999.527803,
    "sameSite": "lax"
  },
  {
    "name": "OTZ",
    "value": "7748002_44_48_171240_44_319500",
    "domain": "ogs.google.com",
    "hostOnly": true,
    "path": "/",
    "secure": true,
    "httpOnly": false,
    "session": false,
    "expirationDate": 1729776124,
    "sameSite": "unspecified"
  },
  {
    "name": "SID",
    "value": "g.a000oQjZJxiDTOAAylq53bEmUQzbhia-QqKcrmltiu8-iJguh3eF-3kBmdOc-BWckx9Js4uR7AACgYKAccSARMSFQHGX2MiLxk7SRgcLaHYpOFM0fyoFxoVAUF8yKoVWyPjMIxO9jr_vDFWWCL00076",
    "domain": ".google.com",
    "hostOnly": false,
    "path": "/",
    "secure": false,
    "httpOnly": false,
    "session": false,
    "expirationDate": 1761744185.602121,
    "sameSite": "unspecified"
  },
  {
    "name": "__Secure-1PSID",
    "value": "g.a000oQjZJxiDTOAAylq53bEmUQzbhia-QqKcrmltiu8-iJguh3eFrf4UEoOYGBvJMQWcV3-ViQACgYKAX4SARMSFQHGX2MiqLlnTmmGRMZhmbVaeG_G4hoVAUF8yKqgRg9Zte9kvygXSBCF8rMl0076",
    "domain": ".google.com",
    "hostOnly": false,
    "path": "/",
    "secure": true,
    "httpOnly": true,
    "session": false,
    "expirationDate": 1761744185.602301,
    "sameSite": "unspecified"
  },
  {
    "name": "__Secure-3PSID",
    "value": "g.a000oQjZJxiDTOAAylq53bEmUQzbhia-QqKcrmltiu8-iJguh3eFYJlCz75Jaj5sC-s-Kg8EigACgYKAdASARMSFQHGX2Miuse91FycogVAhRqHaclQvRoVAUF8yKpLzZxEMUt-QKpV9JWc00sa0076",
    "domain": ".google.com",
    "hostOnly": false,
    "path": "/",
    "secure": true,
    "httpOnly": true,
    "session": false,
    "expirationDate": 1761744185.602489,
    "sameSite": "no_restriction"
  },
  {
    "name": "LSID",
    "value": "s.EG|s.youtube:g.a000oQjZJ-DlQSmU6aM10sW4ZzoMLJ_Y_hRRKbMC6Zea8wgDuJO4tS_qy4z_h6kcHUfV2dxVpAACgYKASoSARMSFQHGX2Mi9csYj788LRARNLbJiEyeshoVAUF8yKpOAjgBc5IEjLWNe63NUy7T0076",
    "domain": "accounts.google.com",
    "hostOnly": true,
    "path": "/",
    "secure": true,
    "httpOnly": true,
    "session": false,
    "expirationDate": 1761744185.602664,
    "sameSite": "unspecified"
  },
  {
    "name": "__Host-1PLSID",
    "value": "s.EG|s.youtube:g.a000oQjZJ-DlQSmU6aM10sW4ZzoMLJ_Y_hRRKbMC6Zea8wgDuJO4orGPaDF8jeVEAK2nyIa-JwACgYKAaUSARMSFQHGX2MiYX5r39INC5zmYzlvsWcdJRoVAUF8yKqNg8r2v_7TguhZZSFl1rOA0076",
    "domain": "accounts.google.com",
    "hostOnly": true,
    "path": "/",
    "secure": true,
    "httpOnly": true,
    "session": false,
    "expirationDate": 1761744185.602848,
    "sameSite": "unspecified"
  },
  {
    "name": "__Host-3PLSID",
    "value": "s.EG|s.youtube:g.a000oQjZJ-DlQSmU6aM10sW4ZzoMLJ_Y_hRRKbMC6Zea8wgDuJO4bkj_v4ubHWogb30oD_Qg2gACgYKAf8SARMSFQHGX2Mixy6smnPM2xqXwcVBHfMDkRoVAUF8yKpMec-DU1jWTtRN5Kx-jnF70076",
    "domain": "accounts.google.com",
    "hostOnly": true,
    "path": "/",
    "secure": true,
    "httpOnly": true,
    "session": false,
    "expirationDate": 1761744185.60302,
    "sameSite": "no_restriction"
  },
  {
    "name": "HSID",
    "value": "ArPDF3VxHlErjznes",
    "domain": ".google.com",
    "hostOnly": false,
    "path": "/",
    "secure": false,
    "httpOnly": true,
    "session": false,
    "expirationDate": 1761744185.603194,
    "sameSite": "unspecified"
  },
  {
    "name": "SSID",
    "value": "AKYgAWrRRnrwu9U7V",
    "domain": ".google.com",
    "hostOnly": false,
    "path": "/",
    "secure": true,
    "httpOnly": true,
    "session": false,
    "expirationDate": 1761744185.603357,
    "sameSite": "unspecified"
  },
  {
    "name": "APISID",
    "value": "-VLeFPEUmnI-yFak/AVElUZHv1Nv0mLqvx",
    "domain": ".google.com",
    "hostOnly": false,
    "path": "/",
    "secure": false,
    "httpOnly": false,
    "session": false,
    "expirationDate": 1761744185.603528,
    "sameSite": "unspecified"
  },
  {
    "name": "SAPISID",
    "value": "qFCZEngYkW7lhz6g/AR3LI8jCf6ohsHbGX",
    "domain": ".google.com",
    "hostOnly": false,
    "path": "/",
    "secure": true,
    "httpOnly": false,
    "session": false,
    "expirationDate": 1761744185.60371,
    "sameSite": "unspecified"
  },
  {
    "name": "__Secure-1PAPISID",
    "value": "qFCZEngYkW7lhz6g/AR3LI8jCf6ohsHbGX",
    "domain": ".google.com",
    "hostOnly": false,
    "path": "/",
    "secure": true,
    "httpOnly": false,
    "session": false,
    "expirationDate": 1761744185.603888,
    "sameSite": "unspecified"
  },
  {
    "name": "__Secure-3PAPISID",
    "value": "qFCZEngYkW7lhz6g/AR3LI8jCf6ohsHbGX",
    "domain": ".google.com",
    "hostOnly": false,
    "path": "/",
    "secure": true,
    "httpOnly": false,
    "session": false,
    "expirationDate": 1761744185.604067,
    "sameSite": "no_restriction"
  },
  {
    "name": "ACCOUNT_CHOOSER",
    "value": "AFx_qI4_HGOc5Xnh5_hZFHzKJaD9sKKakbuIMGb6tgjcOhR1_2x8Czk3CaG2GAZQ7nmFjxWvgzTrpyiBNyFvtrFY6KJXNkYWtWrt9mzcqD8Yd-kIwnzY6m7cQyt5oqMCpHNqcvQk-XIxxhg4Y8_T5p6Hfu6QEEV8Ym1lgvnLGVMLzp36FbM7hOry706eLGNLl3LT6queNncq2fMJkfNdqoImiGDfW1LvlV3i00DGXXXJCmXhHiMOSZg",
    "domain": "accounts.google.com",
    "hostOnly": true,
    "path": "/",
    "secure": true,
    "httpOnly": true,
    "session": false,
    "expirationDate": 1761744185.604263,
    "sameSite": "unspecified"
  },
  {
    "name": "__Host-GAPS",
    "value": "1:KFNqgfkSXzyF6L29XLSvmP_Cypia5Phtyx9W3QcSriUVdQTwuhFTMXUTLAVn6JWt0F2ZHVvpfWItejvY0Ml-ei5L_TSaSg:Qn2kU_l2wgAjRcS4",
    "domain": "accounts.google.com",
    "hostOnly": true,
    "path": "/",
    "secure": true,
    "httpOnly": true,
    "session": false,
    "expirationDate": 1761744185.604446,
    "sameSite": "unspecified"
  },
  {
    "name": "SMSV",
    "value": "ADHTe-B7-Ju36tLYWB0XS3vlGoxbCC1Uq5Sn0ozLwBlc336-sDRhGsYi9SLjcoM4oLCdn-g_XYrixg9UYv433ewKH-WwvnQChKOe0556pxxkIzbew-fU05DjQ_sHNNAOjIM4BfSfG4ufaM32cq1LuLK1G28cY7PcYk14We5mkZop4iPLsc3Hcxg",
    "domain": "accounts.google.com",
    "hostOnly": true,
    "path": "/",
    "secure": true,
    "httpOnly": true,
    "session": false,
    "expirationDate": 1761744185.604625,
    "sameSite": "unspecified"
  },
  {
    "name": "SID",
    "value": "g.a000oQjZJxiDTOAAylq53bEmUQzbhia-QqKcrmltiu8-iJguh3eF-3kBmdOc-BWckx9Js4uR7AACgYKAccSARMSFQHGX2MiLxk7SRgcLaHYpOFM0fyoFxoVAUF8yKoVWyPjMIxO9jr_vDFWWCL00076",
    "domain": ".youtube.com",
    "hostOnly": false,
    "path": "/",
    "secure": false,
    "httpOnly": false,
    "session": false,
    "expirationDate": 1761744185.794282,
    "sameSite": "unspecified"
  },
  {
    "name": "__Secure-1PSIDTS",
    "value": "sidts-CjEBQlrA-Cy6NGsBW7puHEMJ6r817987eX4wcyFkRch1ywMBcacAHK5-76klL-5powg5EAA",
    "domain": ".youtube.com",
    "hostOnly": false,
    "path": "/",
    "secure": true,
    "httpOnly": true,
    "session": false,
    "expirationDate": 1758720185.794542,
    "sameSite": "unspecified"
  },
  {
    "name": "__Secure-3PSIDTS",
    "value": "sidts-CjEBQlrA-Cy6NGsBW7puHEMJ6r817987eX4wcyFkRch1ywMBcacAHK5-76klL-5powg5EAA",
    "domain": ".youtube.com",
    "hostOnly": false,
    "path": "/",
    "secure": true,
    "httpOnly": true,
    "session": false,
    "expirationDate": 1758720185.794728,
    "sameSite": "no_restriction"
  },
  {
    "name": "__Secure-1PSID",
    "value": "g.a000oQjZJxiDTOAAylq53bEmUQzbhia-QqKcrmltiu8-iJguh3eFrf4UEoOYGBvJMQWcV3-ViQACgYKAX4SARMSFQHGX2MiqLlnTmmGRMZhmbVaeG_G4hoVAUF8yKqgRg9Zte9kvygXSBCF8rMl0076",
    "domain": ".youtube.com",
    "hostOnly": false,
    "path": "/",
    "secure": true,
    "httpOnly": true,
    "session": false,
    "expirationDate": 1761744185.794898,
    "sameSite": "unspecified"
  },
  {
    "name": "__Secure-3PSID",
    "value": "g.a000oQjZJxiDTOAAylq53bEmUQzbhia-QqKcrmltiu8-iJguh3eFYJlCz75Jaj5sC-s-Kg8EigACgYKAdASARMSFQHGX2Miuse91FycogVAhRqHaclQvRoVAUF8yKpLzZxEMUt-QKpV9JWc00sa0076",
    "domain": ".youtube.com",
    "hostOnly": false,
    "path": "/",
    "secure": true,
    "httpOnly": true,
    "session": false,
    "expirationDate": 1761744185.795079,
    "sameSite": "no_restriction"
  },
  {
    "name": "HSID",
    "value": "A33wdTmiArYmefjAB",
    "domain": ".youtube.com",
    "hostOnly": false,
    "path": "/",
    "secure": false,
    "httpOnly": true,
    "session": false,
    "expirationDate": 1761744185.79525,
    "sameSite": "unspecified"
  },
  {
    "name": "SSID",
    "value": "ABbyigP3YUrI9XICP",
    "domain": ".youtube.com",
    "hostOnly": false,
    "path": "/",
    "secure": true,
    "httpOnly": true,
    "session": false,
    "expirationDate": 1761744185.795415,
    "sameSite": "unspecified"
  },
  {
    "name": "APISID",
    "value": "-VLeFPEUmnI-yFak/AVElUZHv1Nv0mLqvx",
    "domain": ".youtube.com",
    "hostOnly": false,
    "path": "/",
    "secure": false,
    "httpOnly": false,
    "session": false,
    "expirationDate": 1761744185.795591,
    "sameSite": "unspecified"
  },
  {
    "name": "SAPISID",
    "value": "qFCZEngYkW7lhz6g/AR3LI8jCf6ohsHbGX",
    "domain": ".youtube.com",
    "hostOnly": false,
    "path": "/",
    "secure": true,
    "httpOnly": false,
    "session": false,
    "expirationDate": 1761744185.79576,
    "sameSite": "unspecified"
  },
  {
    "name": "__Secure-1PAPISID",
    "value": "qFCZEngYkW7lhz6g/AR3LI8jCf6ohsHbGX",
    "domain": ".youtube.com",
    "hostOnly": false,
    "path": "/",
    "secure": true,
    "httpOnly": false,
    "session": false,
    "expirationDate": 1761744185.795932,
    "sameSite": "unspecified"
  },
  {
    "name": "__Secure-3PAPISID",
    "value": "qFCZEngYkW7lhz6g/AR3LI8jCf6ohsHbGX",
    "domain": ".youtube.com",
    "hostOnly": false,
    "path": "/",
    "secure": true,
    "httpOnly": false,
    "session": false,
    "expirationDate": 1761744185.796138,
    "sameSite": "no_restriction"
  },
  {
    "name": "SID",
    "value": "g.a000oQjZJxiDTOAAylq53bEmUQzbhia-QqKcrmltiu8-iJguh3eF-3kBmdOc-BWckx9Js4uR7AACgYKAccSARMSFQHGX2MiLxk7SRgcLaHYpOFM0fyoFxoVAUF8yKoVWyPjMIxO9jr_vDFWWCL00076",
    "domain": ".google.com.eg",
    "hostOnly": false,
    "path": "/",
    "secure": false,
    "httpOnly": false,
    "session": false,
    "expirationDate": 1761744185.946311,
    "sameSite": "unspecified"
  },
  {
    "name": "__Secure-1PSID",
    "value": "g.a000oQjZJxiDTOAAylq53bEmUQzbhia-QqKcrmltiu8-iJguh3eFrf4UEoOYGBvJMQWcV3-ViQACgYKAX4SARMSFQHGX2MiqLlnTmmGRMZhmbVaeG_G4hoVAUF8yKqgRg9Zte9kvygXSBCF8rMl0076",
    "domain": ".google.com.eg",
    "hostOnly": false,
    "path": "/",
    "secure": true,
    "httpOnly": true,
    "session": false,
    "expirationDate": 1761744185.946567,
    "sameSite": "unspecified"
  },
  {
    "name": "__Secure-3PSID",
    "value": "g.a000oQjZJxiDTOAAylq53bEmUQzbhia-QqKcrmltiu8-iJguh3eFYJlCz75Jaj5sC-s-Kg8EigACgYKAdASARMSFQHGX2Miuse91FycogVAhRqHaclQvRoVAUF8yKpLzZxEMUt-QKpV9JWc00sa0076",
    "domain": ".google.com.eg",
    "hostOnly": false,
    "path": "/",
    "secure": true,
    "httpOnly": true,
    "session": false,
    "expirationDate": 1761744185.946758,
    "sameSite": "no_restriction"
  },
  {
    "name": "HSID",
    "value": "A33wdTmiArYmefjAB",
    "domain": ".google.com.eg",
    "hostOnly": false,
    "path": "/",
    "secure": false,
    "httpOnly": true,
    "session": false,
    "expirationDate": 1761744185.946942,
    "sameSite": "unspecified"
  },
  {
    "name": "SSID",
    "value": "ABbyigP3YUrI9XICP",
    "domain": ".google.com.eg",
    "hostOnly": false,
    "path": "/",
    "secure": true,
    "httpOnly": true,
    "session": false,
    "expirationDate": 1761744185.947105,
    "sameSite": "unspecified"
  },
  {
    "name": "APISID",
    "value": "-VLeFPEUmnI-yFak/AVElUZHv1Nv0mLqvx",
    "domain": ".google.com.eg",
    "hostOnly": false,
    "path": "/",
    "secure": false,
    "httpOnly": false,
    "session": false,
    "expirationDate": 1761744185.947267,
    "sameSite": "unspecified"
  },
  {
    "name": "SAPISID",
    "value": "qFCZEngYkW7lhz6g/AR3LI8jCf6ohsHbGX",
    "domain": ".google.com.eg",
    "hostOnly": false,
    "path": "/",
    "secure": true,
    "httpOnly": false,
    "session": false,
    "expirationDate": 1761744185.947438,
    "sameSite": "unspecified"
  },
  {
    "name": "__Secure-1PAPISID",
    "value": "qFCZEngYkW7lhz6g/AR3LI8jCf6ohsHbGX",
    "domain": ".google.com.eg",
    "hostOnly": false,
    "path": "/",
    "secure": true,
    "httpOnly": false,
    "session": false,
    "expirationDate": 1761744185.947617,
    "sameSite": "unspecified"
  },
  {
    "name": "__Secure-3PAPISID",
    "value": "qFCZEngYkW7lhz6g/AR3LI8jCf6ohsHbGX",
    "domain": ".google.com.eg",
    "hostOnly": false,
    "path": "/",
    "secure": true,
    "httpOnly": false,
    "session": false,
    "expirationDate": 1761744185.947795,
    "sameSite": "no_restriction"
  },
  {
    "name": "NID",
    "value": "517=FdR5GuIPvjtNk-Ep10m4AAvCUJdFME7hM3fTxIr87uuiQQwGjX6633J6UGwj8e_5pBnJOU0j23iqrMItpw48mWmwEIKYEziLURrAiODpeCCOhnsEZrL1NjQt6RHGtWltmRRAZFGyrafeGuhX2AH6caGuw0BV3JoBQoT_qr7-7Xp2M4bmqkA4IHkvN-4OHjuBh4OP_OKtHb_CSxq3fxq40vU7yMudg73xzDQiZonRv1_9J-m4ycUu9ezqnXBI2tnAal87r9JJk7KBq061EP8HronkA6GYb9TmIuRhIlMowqYAeSim4ddPD9AHnbBxPGFczXz68OTrGCHaf7ZafiwER28kHm-GmnLGuGIAMdllQ_zpB9gKI67FpD_6GBamz0nIz-2OZ-UqD1L5top463KZ6k1rM7N3HrV4NRjtEU1PkCFieSJ9QweryCBrNc2JaF29mqTOn6w1lGDTvRiCcTxMJxNBfFfLxlh9ELbblGB0qk5ivEhdFh9KZMvNYsLmZWMaDB21Jgl2U9R5lOXcgjxKX2r0U25PxdX2zmj665B5WamL7WTdOm7rVI2WzMpyBRUwb6-SIB7v7I35jA9AI1Q9SQogAgfs_XO5-tSKNTCHj1VNuf7fb4wDekviUf9WwFtBtmQwC-bLB5DNGH8hwRmi6YRNQ1LXYFz8w-2QKiKh6yunoVqd0vUm5dJFrMd2By6C",
    "domain": ".google.com.eg",
    "hostOnly": false,
    "path": "/",
    "secure": true,
    "httpOnly": true,
    "session": false,
    "expirationDate": 1742995320.947961,
    "sameSite": "no_restriction"
  },
  {
    "name": "SEARCH_SAMESITE",
    "value": "CgQIl5wB",
    "domain": ".google.com",
    "hostOnly": false,
    "path": "/",
    "secure": false,
    "httpOnly": false,
    "session": false,
    "expirationDate": 1742802737.721024,
    "sameSite": "strict"
  },
  {
    "name": "DV",
    "value": "04mMoZ2Sw1JVACJ-bZgLX57Nm6iCIplw4P5MyRCtQwMAAMDG-w71jj8zIgEAAPA12Tp0snLFWwAAAB7d8Xg8VY-nGAAAAA",
    "domain": "www.google.com",
    "hostOnly": true,
    "path": "/",
    "secure": false,
    "httpOnly": false,
    "session": false,
    "expirationDate": 1727251331,
    "sameSite": "unspecified"
  },
  {
    "name": "__Secure-1PSIDTS",
    "value": "sidts-CjEBQlrA-NSjao1F5jBtwXCwE1kEKDB1JKW18r8IAkk-VFgU95YyC_LoyHDgwbOYNxMkEAA",
    "domain": ".google.com",
    "hostOnly": false,
    "path": "/",
    "secure": true,
    "httpOnly": true,
    "session": false,
    "expirationDate": 1758786733.096108,
    "sameSite": "unspecified"
  },
  {
    "name": "__Secure-3PSIDTS",
    "value": "sidts-CjEBQlrA-NSjao1F5jBtwXCwE1kEKDB1JKW18r8IAkk-VFgU95YyC_LoyHDgwbOYNxMkEAA",
    "domain": ".google.com",
    "hostOnly": false,
    "path": "/",
    "secure": true,
    "httpOnly": true,
    "session": false,
    "expirationDate": 1758786733.096377,
    "sameSite": "no_restriction"
  },
  {
    "name": "NID",
    "value": "517=h4W6A9UNSH7B8LoGPm9LrP0TJEEwcblfJRJOIxUsXx3y-y1iIW66mBwFcOB9RUV0jlMMpPo-QuaEyNlIqftIMliVaeKz9l-6UaTuUGdsRRRTq_MGJ691e8LiZrBuzgjSwUdikaHPpjKHr8NQBcTIBguiMNDkheMcXH2YHTvNeiQnCpsGYV1P5U2XryyiNZk8O-UrPYcsztKcO0FNpp2KVZjkgWH7Tkfk4vOmURq9F6qZ7lMbCE9pQPA89L7HroafsosUsnTlRIuEHRdb5wcys6wHTtq0RLo8CqAld13prGIR2zkBB0kbyyxjuZb22GwhhRzH8La2vqxerwk6TWAV6HfqWSIkwftsqS3LafzQwBPiZFIGS8V-ZRLzjsSL4Q2vKwtvwm6hqJheWhcJlnk4sh-natnaZbTfliXEjxnE40IXc3hgM-HnTpE-ib00JZzXkmJPDNGhiaHlinynO-lto7e40IDyRe6Jl486yRdg9usSflk-1gxPOQdspN4tajf5D4v7b-INnYhOoH050jz7Dx4Pzq_-hy2kzRos7T6J3G32NE_ruIPGilBQD738wfVPoRrrZmUAdnXg3Wux_Rc-MkXPFCUTDyj9jaoMVlxJBFh34cPesripHwFZxdpbG3qP8VNLZitTDT_vLmjTUlBo5NQaLlYECBklkHcyAGgTTGgNGCfHgb1tVvHOX6zmWpg_HbyC2VKyv6_tWMwiaCy0nALjREWJV1cv0CFo_ScDVxTFPz7fWHwO6pnH3ZaBQGIpPicXYmIBJVOqt6uIqlfO-xMdr2yhi56W8KL3R9kP1Cf81gckfDf5Jka3QpF1uyJ2lqCLUUPYhKg3RAcNZnLHQUTCBjSZo7qPmBGkoDIQ3w0sAkwj4hdDJMdLTI44tIoVTLAE2mLEZYN3CYlKCwlATFn-lWss1-YF6PnP2zj-6lmtUnNqPrvbuynWh1gNIfwCJKZrj30JIqQcuOtes_7KcAYsZnYHaQadSXytEkbhPkOrttnkpOz2FX0wKarVZyGHkX6WiYc1YUP5C4cZ2jW4DfWu5mizihI1rr7NRgWVGHXWMwVoL1Fbn0iBsOp-69HlmItDBimjUEeVuVsLsshJJ5hZTHByLr3UZhO6QqglyGRu_2bStuTAP5_g380f0H7RhiYG1RPLuHZaTySlmHEy",
    "domain": ".google.com",
    "hostOnly": false,
    "path": "/",
    "secure": true,
    "httpOnly": true,
    "session": false,
    "expirationDate": 1743061930.721253,
    "sameSite": "no_restriction"
  },
  {
    "name": "SIDCC",
    "value": "AKEyXzWUv0rVCJSNoxBybILz3yVfDmwpLEyfht9e0CzJFrUqv5L_T6erj8TOMbOr01DQ4cdlYQ",
    "domain": ".google.com",
    "hostOnly": false,
    "path": "/",
    "secure": false,
    "httpOnly": false,
    "session": false,
    "expirationDate": 1758786740.45898,
    "sameSite": "unspecified"
  },
  {
    "name": "__Secure-1PSIDCC",
    "value": "AKEyXzV4l92IPY2UFQfG48Vllq3SKicV9x2ZQTXNduVfECNIniVMZWztqG5G4_b74ilDpWaBffk",
    "domain": ".google.com",
    "hostOnly": false,
    "path": "/",
    "secure": true,
    "httpOnly": true,
    "session": false,
    "expirationDate": 1758786740.459165,
    "sameSite": "unspecified"
  },
  {
    "name": "__Secure-3PSIDCC",
    "value": "AKEyXzUoiMZQu5CfY97HEt9Gmbk9LGpcaxh7jTFmxlaYOIkyEQwba4wyUtTOfRiZ5geuwIhX0XM",
    "domain": ".google.com",
    "hostOnly": false,
    "path": "/",
    "secure": true,
    "httpOnly": true,
    "session": false,
    "expirationDate": 1758786740.459358,
    "sameSite": "no_restriction"
  }
]